{
  "id": "hanoi–transition"
  "title": "Hanoi – Transition",
  "abstract": "Streets of Hanoi, on the day of the three kitchen guardians brought inside out at a public square in Potsdam, Germany.",
  "filminfo": "2011, 21:00 min.",
  "credits": [
    "Concept & Realisation by Trang Nguyen",
    "Graphics & Animation by Roman Bejnar"      
  ],
  "festivals": [
    "Agora Artes-Probelauf, Akademie der Künste 2013",
    "Montage-Experiment-Reflexion Symposium, Potsdam 2013",
    "Open Day, Film University, Potsdam 2011"
  ],
  "awards": [
  
  ],
  "vidSrc": "https://player.vimeo.com/video/52103917?title=0&byline=0&portrait=0&color=ff5025",
  "tags": "installation",
  "poster": "filmposters/hanoi-transition.jpg"  
}